moex/__init__.py
moex/finance.py
moex/moex.py
pymoex-0.0.2.dist-info/LICENSE
pymoex-0.0.2.dist-info/METADATA
pymoex-0.0.2.dist-info/WHEEL
pymoex-0.0.2.dist-info/top_level.txt
pymoex-0.0.2.dist-info/RECORD
